gcandle/__init__.py
gcandle/core/DayBarCandidatesScanner.py
gcandle/core/__init__.py
gcandle/core/backtest_analysis.py
gcandle/core/common_types.py
gcandle/core/strategy_analyzer.py
gcandle/core/backtest/AccountPositionStock.py
gcandle/core/backtest/RiskIndicator.py
gcandle/core/backtest/__init__.py
gcandle/core/backtest/backtest_accounting.py
gcandle/core/backtest/day_bar_backtest.py
gcandle/core/backtest/seposition.py
gcandle/core/buy_strategy/BuyStrategy.py
gcandle/core/buy_strategy/__init__.py
gcandle/core/indicator_service/__init__.py
gcandle/core/indicator_service/fp_mark_service.py
gcandle/core/indicator_service/indicator_db_service.py
gcandle/core/indicator_service/indicator_service.py
gcandle/core/indicator_service/master_indicator_db.py
gcandle/core/indicator_service/master_indicator_service.py
gcandle/core/indicator_service/slave_indicator_service.py
gcandle/core/sell_strategy/AbstractSellStrategy.py
gcandle/core/sell_strategy/CombinedSellStrategy.py
gcandle/core/sell_strategy/SellAtCloseStrategy.py
gcandle/core/sell_strategy/SellAtOpenStrategy.py
gcandle/core/sell_strategy/TargetPriceSellStrategy.py
gcandle/core/sell_strategy/__init__.py
gcandle/data/QfqTransformer.py
gcandle/data/SecurityDataService.py
gcandle/data/SecurityDataUpdateMonitor.py
gcandle/data/SecurityDataVerifier.py
gcandle/data/SecurityFetcher.py
gcandle/data/__init__.py
gcandle/data/se_types.py
gcandle/data/csv/CsvSecurityFetcher.py
gcandle/data/csv/__init__.py
gcandle/data/csv/update_csv_min_bars.py
gcandle/data/csv_data/CsvSecurityFetcher.py
gcandle/data/csv_data/__init__.py
gcandle/data/csv_data/update_csv_min_bars.py
gcandle/data/tdx/TdxSecurityFetcher.py
gcandle/data/tdx/__init__.py
gcandle/data/tdx/update_tdx.py
gcandle/data/tdx/update_tdx_min_bars.py
gcandle/indicator/__init__.py
gcandle/indicator/basic_indicators.py
gcandle/indicator/day_fp_marks.py
gcandle/indicator/fp_feature_service.py
gcandle/indicator/fuquan.py
gcandle/indicator/macd.py
gcandle-0.0.11.dist-info/METADATA
gcandle-0.0.11.dist-info/WHEEL
gcandle-0.0.11.dist-info/top_level.txt
gcandle-0.0.11.dist-info/RECORD
