Metadata-Version: 2.1
Name: gcandle
Version: 0.0.11
Summary: A library for quant trade
Home-page: https://github.com/yangchanghua/gcandle
Author: ych
Author-email: yangchanghua@gmail.com
License: UNKNOWN
Platform: UNKNOWN
Classifier: Programming Language :: Python :: 3
Classifier: License :: OSI Approved :: GNU General Public License v3 (GPLv3)
Classifier: Operating System :: OS Independent
Requires-Python: >=3.6
Requires-Dist: pandas
Requires-Dist: numpy
Requires-Dist: pymongo
Requires-Dist: matplotlib
Requires-Dist: pytdx
